tabulate.py
tabulate_expwidth-0.9.0.1.3.8.dist-info/LICENSE
tabulate_expwidth-0.9.0.1.3.8.dist-info/METADATA
tabulate_expwidth-0.9.0.1.3.8.dist-info/WHEEL
tabulate_expwidth-0.9.0.1.3.8.dist-info/entry_points.txt
tabulate_expwidth-0.9.0.1.3.8.dist-info/top_level.txt
tabulate_expwidth-0.9.0.1.3.8.dist-info/RECORD
