Metadata-Version: 2.1
Name: tabulate-expwidth
Version: 0.9.0.1.3.8
Summary: Pretty-print tabular data
Home-page: https://github.com/mhuang001/python-tabulate.git@r1
Author: M. Huang (Orig. Sergey Astanin)
Author-email: mhuang001@gitub.com
License: MIT
Platform: UNKNOWN
Classifier: Development Status :: 4 - Beta
Classifier: License :: OSI Approved :: MIT License
Classifier: Operating System :: OS Independent
Classifier: Programming Language :: Python :: 3
Classifier: Programming Language :: Python :: 3.6
Classifier: Programming Language :: Python :: 3.7
Classifier: Programming Language :: Python :: 3.8
Classifier: Programming Language :: Python :: 3.9
Classifier: Programming Language :: Python :: 3.10
Classifier: Programming Language :: Python :: 3 :: Only
Classifier: Topic :: Software Development :: Libraries
Requires-Python: >=3.6
License-File: LICENSE
Provides-Extra: widechars
Requires-Dist: wcwidth ; extra == 'widechars'
